<?xml version="1.0" encoding="utf-8"?>
<manifest>
	<policy-version>0.1.0</policy-version>
	<policy-group name="application">
		<policy name="package-installation-mode">allowed</policy>
		<policy name="package-uninstallation-mode">allowed</policy>
	</policy-group>
	<policy-group name="password">
		<policy name="password-quality">0</policy>
		<policy name="password-minimum-length">0</policy>
		<policy name="password-maximum-failure-count">0</policy>
		<policy name="password-expired">0</policy>
		<policy name="password-minimum-complexity">0</policy>
		<policy name="password-pattern"></policy>
		<policy name="password-history">0</policy>
		<policy name="password-recovery">0</policy>
		<policy name="password-lock-delay">0</policy>
		<policy name="password-inactivity-timeout">0</policy>
		<policy name="password-status">0</policy>
		<policy name="password-change-timeout">0</policy>
		<policy name="password-maximum-character-occurrences">0</policy>
		<policy name="password-numeric-sequences-length">0</policy>
		<policy name="password-forbidden-strings"></policy>
	</policy-group>
	<policy-group name="security">
		<policy name="internal-storage-encryption">allowed</policy>
		<policy name="external-storage-encryption">allowed</policy>
		<policy name="internet-sharing">allowed</policy>
		<policy name="require-device-encryption">allowed</policy>
		<policy name="require-sdcard-encryption">allowed</policy>
	</policy-group>
	<policy-group name="wifi">
		<policy name="wifi-profile-change">allowed</policy>
		<policy name="wifi-ssid-restriction">disabled</policy>
	</policy-group>
	<policy-group name="bluetooth">
		<policy name="bluetooth-paring">allowed</policy>
		<policy name="bluetooth-outgoing-call">allowed</policy>
		<policy name="bluetooth-profile-a2dp">allowed</policy>
		<policy name="bluetooth-profile-avrcp">allowed</policy>
		<policy name="bluetooth-profile-bpp">allowed</policy>
		<policy name="bluetooth-profile-dun">allowed</policy>
		<policy name="bluetooth-profile-ftp">allowed</policy>
		<policy name="bluetooth-profile-hfp">allowed</policy>
		<policy name="bluetooth-profile-hsp">allowed</policy>
		<policy name="bluetooth-profile-pbap">allowed</policy>
		<policy name="bluetooth-profile-sap">allowed</policy>
		<policy name="bluetooth-profile-spp">allowed</policy>
		<policy name="bluetooth-desktop-connectivity">allowed</policy>
		<policy name="bluetooth-descoverable">allowed</policy>
		<policy name="bluetooth-limited-discoverable">allowed</policy>
		<policy name="bluetooth-data-transfer">allowed</policy>
		<policy name="bluetooth-uuid-restriction">disabled</policy>
		<policy name="bluetooth-device-restriction">disabled</policy>
	</policy-group>
	<policy-group name="restriction">
		<policy name="wifi">allowed</policy>
		<policy name="wifi-hotspot">allowed</policy>
		<policy name="bluetooth">allowed</policy>
		<policy name="camera">allowed</policy>
		<policy name="microphone">allowed</policy>
		<policy name="location">allowed</policy>
		<policy name="external-storage">allowed</policy>
		<policy name="text-messaging">allowed</policy>
		<policy name="pop-imap-email">allowed</policy>
		<policy name="browser">allowed</policy>
		<policy name="settings-changes">allowed</policy>
		<policy name="tethering">allowed</policy>
		<policy name="bluetooth-tethering">allowed</policy>
		<policy name="clipboard">allowed</policy>
		<policy name="screen-capture">allowed</policy>
		<policy name="usb-debugging">allowed</policy>
		<policy name="usb-tethering">allowed</policy>
	</policy-group>
	<policy-group name="browser">
		<policy name="browser-autofill-setting">allowed</policy>
		<policy name="browser-cookies-setting">allowed</policy>
		<policy name="force-fraud-warning_setting">allowed</policy>
		<policy name="javascript-setting">allowed</policy>
		<policy name="popup-setting">allowed</policy>
	</policy-group>
</manifest>
